waste_management/Entities.py
waste_management/__init__.py
waste_management/__main__.py
waste_management/client.py
waste_management/const.py
waste_management-3.1.1.dist-info/METADATA
waste_management-3.1.1.dist-info/WHEEL
waste_management-3.1.1.dist-info/top_level.txt
waste_management-3.1.1.dist-info/RECORD
