Metadata-Version: 2.1
Name: waste-management
Version: 3.1.1
Summary: Provides ability to query the Waste Management REST API.
Home-page: https://github.com/dcmeglio/waste_management
Author: Dominick Meglio
Author-email: dmeglio@gmail.com
License: MIT
Classifier: Programming Language :: Python :: 3
Classifier: License :: OSI Approved :: MIT License
Classifier: Operating System :: OS Independent
Requires-Python: >=3.6
Requires-Dist: pyjwt
Requires-Dist: httpx
